homingpigeon/__init__.py
homingpigeon/senddata.py
HomingPigeon-1.0.dist-info/LICENSE
HomingPigeon-1.0.dist-info/METADATA
HomingPigeon-1.0.dist-info/WHEEL
HomingPigeon-1.0.dist-info/top_level.txt
HomingPigeon-1.0.dist-info/RECORD
